python_alfresco_api/__init__.py
python_alfresco_api/auth_util.py
python_alfresco_api/client_factory.py
python_alfresco_api/clients/__init__.py
python_alfresco_api/clients/conversion_utils.py
python_alfresco_api/clients/field_mapping.py
python_alfresco_api/clients/master_client.py
python_alfresco_api/clients/models.py
python_alfresco_api/clients/auth/__init__.py
python_alfresco_api/clients/auth/auth_client.py
python_alfresco_api/clients/auth/models.py
python_alfresco_api/clients/auth/authentication/__init__.py
python_alfresco_api/clients/auth/authentication/authentication_client.py
python_alfresco_api/clients/auth/authentication/models.py
python_alfresco_api/clients/core/__init__.py
python_alfresco_api/clients/core/core_client.py
python_alfresco_api/clients/core/models.py
python_alfresco_api/clients/core/actions/__init__.py
python_alfresco_api/clients/core/actions/actions_client.py
python_alfresco_api/clients/core/actions/models.py
python_alfresco_api/clients/core/activities/__init__.py
python_alfresco_api/clients/core/activities/activities_client.py
python_alfresco_api/clients/core/activities/models.py
python_alfresco_api/clients/core/audit/__init__.py
python_alfresco_api/clients/core/audit/audit_client.py
python_alfresco_api/clients/core/audit/models.py
python_alfresco_api/clients/core/comments/__init__.py
python_alfresco_api/clients/core/comments/comments_client.py
python_alfresco_api/clients/core/comments/models.py
python_alfresco_api/clients/core/content/__init__.py
python_alfresco_api/clients/core/content/content_client.py
python_alfresco_api/clients/core/content/models.py
python_alfresco_api/clients/core/downloads/__init__.py
python_alfresco_api/clients/core/downloads/downloads_client.py
python_alfresco_api/clients/core/downloads/models.py
python_alfresco_api/clients/core/favorites/__init__.py
python_alfresco_api/clients/core/favorites/favorites_client.py
python_alfresco_api/clients/core/favorites/models.py
python_alfresco_api/clients/core/groups/__init__.py
python_alfresco_api-1.1.5.dist-info/METADATA
python_alfresco_api-1.1.5.dist-info/WHEEL
python_alfresco_api-1.1.5.dist-info/licenses/LICENSE
python_alfresco_api-1.1.5.dist-info/RECORD
