Metadata-Version: 2.4
Name: python-alfresco-api
Version: 1.1.5
Summary: Python Client for all Alfresco Content Services REST APIs, with Pydantic v2 Models, and Event Support
Project-URL: Homepage, https://github.com/stevereiner/python-alfresco-api
Project-URL: Repository, https://github.com/stevereiner/python-alfresco-api
Project-URL: Documentation, https://github.com/stevereiner/python-alfresco-api/docs
Project-URL: Bug Tracker, https://github.com/stevereiner/python-alfresco-api/issues
Author-email: Steve Reiner <example@example.com>
License: Apache-2.0
License-File: LICENSE
Keywords: alfresco,content-management,document-management,ecm,rest-api
Classifier: Development Status :: 5 - Production/Stable
Classifier: Intended Audience :: Developers
Classifier: License :: OSI Approved :: Apache Software License
Classifier: Programming Language :: Python :: 3
Classifier: Programming Language :: Python :: 3.10
Classifier: Programming Language :: Python :: 3.11
Classifier: Programming Language :: Python :: 3.12
Classifier: Programming Language :: Python :: 3.13
Classifier: Topic :: Office/Business :: Office Suites
Classifier: Topic :: Software Development :: Libraries :: Python Modules
Requires-Python: >=3.10
Requires-Dist: attrs>=23.1.0
Requires-Dist: httpx>=0.25.0
Requires-Dist: pydantic>=2.0.0
Requires-Dist: python-dateutil>=2.8.0
Requires-Dist: pyyaml>=6.0
Requires-Dist: stomp-py>=8.1.0
Requires-Dist: typing-extensions>=4.7.0
Provides-Extra: dev
Requires-Dist: black>=23.0.0; extra == 'dev'
Requires-Dist: mypy>=1.5.0; extra == 'dev'
Requires-Dist: pytest-asyncio>=0.21.0; extra == 'dev'
Requires-Dist: pytest>=7.4.0; extra == 'dev'
Provides-Extra: test
Requires-Dist: httpx>=0.25.0; extra == 'test'
Requires-Dist: pytest-asyncio>=0.21.0; extra == 'test'
Requires-Dist: pytest-mock>=3.12.0; extra == 'test'
Requires-Dist: pytest>=7.4.0; extra == 'test'
